neosr/__init__.py
neosr/archs/__init__.py
neosr/archs/arch_util.py
neosr/archs/atd_arch.py
neosr/archs/compact_arch.py
neosr/archs/craft_arch.py
neosr/archs/cugan_arch.py
neosr/archs/dat_arch.py
neosr/archs/dctlsa_arch.py
neosr/archs/ditn_arch.py
neosr/archs/drct_arch.py
neosr/archs/ea2fpn_arch.py
neosr/archs/eimn_arch.py
neosr/archs/esrgan_arch.py
neosr/archs/grformer_arch.py
neosr/archs/hat_arch.py
neosr/archs/hitsrf_arch.py
neosr/archs/hma_arch.py
neosr/archs/man_arch.py
neosr/archs/mosr_arch.py
neosr/archs/msdan_arch.py
neosr/archs/omnisr_arch.py
neosr/archs/patchgan_arch.py
neosr/archs/plksr_arch.py
neosr/archs/realplksr_arch.py
neosr/archs/rgt_arch.py
neosr/archs/safmn_arch.py
neosr/archs/span_arch.py
neosr/archs/spanplus_arch.py
neosr/archs/srformer_arch.py
neosr/archs/swinir_arch.py
neosr/archs/unet_arch.py
neosr/archs/vgg_arch.py
neosr/data/__init__.py
neosr/data/augmentations.py
neosr/data/data_sampler.py
neosr/data/data_util.py
neosr/data/degradations.py
neosr/data/file_client.py
neosr/data/otf_dataset.py
neosr/data/paired_dataset.py
neosr/data/prefetch_dataloader.py
neosr/data/single_dataset.py
neosr/data/transforms.py
neosr/losses/__init__.py
neosr/losses/basic_loss.py
neosr/losses/consistency_loss.py
neosr/losses/dists_loss.py
neosr/losses/dists_weights.pth
neosr/losses/ff_loss.py
neosr/losses/gan_loss.py
neosr/losses/gw_loss.py
neosr/losses/ldl_loss.py
neosr/losses/ssim_loss.py
neosr/losses/vgg_perceptual_loss.py
neosr/losses/wavelet_guided.py
neosr/metrics/__init__.py
neosr/metrics/calculate.py
neosr/metrics/metric_util.py
neosr/models/__init__.py
neosr/models/base.py
neosr/models/image.py
neosr/models/otf.py
neosr/optimizers/__init__.py
neosr/optimizers/adamw_sf.py
neosr/optimizers/adamw_win.py
neosr/optimizers/adan.py
neosr/optimizers/adan_sf.py
neosr/optimizers/fsam.py
neosr/utils/__init__.py
neosr/utils/color_util.py
neosr/utils/diffjpeg.py
neosr/utils/dist_util.py
neosr/utils/img_util.py
neosr/utils/lmdb_util.py
neosr/utils/logger.py
neosr-0.1.0.dist-info/METADATA
neosr-0.1.0.dist-info/WHEEL
neosr-0.1.0.dist-info/RECORD
