Metadata-Version: 2.1
Name: neosr
Version: 0.1.0
Summary: neosr, a framework for training real-world single-image super-resolution networks.
License: Apache 2.0
Author: musl
Requires-Python: >=3.12,<4.0
Classifier: License :: Other/Proprietary License
Classifier: Programming Language :: Python :: 3
Classifier: Programming Language :: Python :: 3.12
Requires-Dist: einops (>=0.6.1,<0.7.0)
Requires-Dist: lmdb (>=1.5.1,<2.0.0)
Requires-Dist: numpy (>=1.25.2,<2.0.0)
Requires-Dist: opencv-python-headless (>=4.8.1.78,<5.0.0.0)
Requires-Dist: pywavelets (>=1.5.0,<2.0.0)
Requires-Dist: scipy (>=1.11.1,<2.0.0)
Requires-Dist: tb-nightly (>=2.18.0a20240708,<3.0.0)
Requires-Dist: tqdm (>=4.65.0,<5.0.0)
